{"2023-1":[{"title":"Hello World","date":"2023-01-16T04:00:00.000Z","link":"/posts/20230126/"}],"2023-2":[{"title":"Day1:目录","date":"2023-02-01T04:00:00.000Z","link":"/posts/20230201/"},{"title":"Day2:赛事链接","date":"2023-02-02T04:00:00.000Z","link":"/posts/20230202/"},{"title":"Day3:解题流程示例","date":"2023-02-03T04:00:00.000Z","link":"/posts/20230203/"},{"title":"Day4:试题链接列表","date":"2023-02-04T04:00:00.000Z","link":"/posts/20230204/"},{"title":"Day5:Buffer5","date":"2023-02-05T04:00:00.000Z","link":"/posts/20230205/"},{"title":"Day6-7:2023第一期模拟赛","date":"2023-02-07T04:00:00.000Z","link":"/posts/2023020607/"},{"title":"Day8-9:2023第二期模拟赛","date":"2023-02-09T04:00:00.000Z","link":"/posts/2023020809/"},{"title":"Day10-15:题库真题：2021-2022年15+5","date":"2023-02-15T04:00:00.000Z","link":"/posts/2023021015/"},{"title":"DayTest2021:2021年第十二届省赛真题","date":"2023-02-16T04:00:00.000Z","link":"/posts/202303test2021/"},{"title":"Day14-17:题库真题：2019-2020年15+5","date":"2023-02-17T04:00:00.000Z","link":"/posts/2023021417/"},{"title":"Day18-24:题库真题：2017-2018年15+5","date":"2023-02-24T04:00:00.000Z","link":"/posts/2023021824/"}],"2023-3":[{"title":"record1:目录","date":"2023-03-03T03:00:00.000Z","link":"/posts/20230303r/"},{"title":"record2:赛事链接","date":"2023-03-03T04:00:00.000Z","link":"/posts/20230303r1/"},{"title":"record3:备赛经验总结","date":"2023-03-04T03:00:00.000Z","link":"/posts/20230304r/"},{"title":"record4:电赛小车解决方案分析","date":"2023-03-04T03:30:00.000Z","link":"/posts/20230304r1/"},{"title":"Day28+4:题库真题：2015-2016年7+3","date":"2023-03-04T04:00:00.000Z","link":"/posts/20230304/"},{"title":"Day28+5:2023第三期模拟赛","date":"2023-03-05T04:00:00.000Z","link":"/posts/20230305/"},{"title":"record5:电赛模块知识","date":"2023-03-08T04:00:00.000Z","link":"/posts/20230308r/"},{"title":"DayALG_DFS:DFS算法真题","date":"2023-03-08T04:00:00.000Z","link":"/posts/20230308/"},{"title":"DayALG_BFS:BFS算法真题","date":"2023-03-10T04:00:00.000Z","link":"/posts/20230310/"},{"title":"record6:模块购买清单","date":"2023-03-13T03:00:00.000Z","link":"/posts/20230313r/"},{"title":"record7:必备软件","date":"2023-03-14T03:00:00.000Z","link":"/posts/20230314r/"},{"title":"chapter1","date":"2023-03-15T04:00:00.000Z","link":"/posts/20230315c/"},{"title":"Unit1","date":"2023-03-15T05:00:00.000Z","link":"/posts/20230315c1/"},{"title":"Daily1-20:1随机题10+10","date":"2023-03-18T04:00:00.000Z","link":"/posts/202303daily1/"},{"title":"chapter2","date":"2023-03-19T04:00:00.000Z","link":"/posts/20230319c/"},{"title":"Unit2","date":"2023-03-19T05:00:00.000Z","link":"/posts/20230319c1/"},{"title":"DayALG_DP&01bag:DP算法与01背包问题","date":"2023-03-20T04:00:00.000Z","link":"/posts/20230320/"},{"title":"Unit3","date":"2023-03-21T05:00:00.000Z","link":"/posts/20230321c1/"},{"title":"DayTest2022:2022年第十三届省赛真题","date":"2023-03-22T04:00:00.000Z","link":"/posts/202303test2022/"},{"title":"DayTest2020:2020年第十一届省赛真题","date":"2023-03-23T04:00:00.000Z","link":"/posts/202303test2020/"},{"title":"Daily2-20:2随机题10+10","date":"2023-03-24T04:00:00.000Z","link":"/posts/202303daily2/"},{"title":"Unit4","date":"2023-03-24T05:00:00.000Z","link":"/posts/20230324c1/"},{"title":"Unit5","date":"2023-03-27T05:00:00.000Z","link":"/posts/20230327c1/"},{"title":"DayEND_knowledge:蓝桥杯知识总结","date":"2023-03-31T04:00:00.000Z","link":"/posts/2023030131/"},{"title":"DayEND_algorithm:蓝桥杯算法总结","date":"2023-03-31T04:00:00.000Z","link":"/posts/2023030031/"}],"2023-4":[{"title":"DayEasy:简易题","date":"2023-04-01T04:00:00.000Z","link":"/posts/20230401/"},{"title":"Fight-Songs","date":"2023-04-08T04:00:00.000Z","link":"/posts/2023fightsongs/"}]}